webcrawlerapi_langchain/__init__.py
webcrawlerapi_langchain/loader.py
webcrawlerapi_langchain-0.1.1.dist-info/METADATA
webcrawlerapi_langchain-0.1.1.dist-info/WHEEL
webcrawlerapi_langchain-0.1.1.dist-info/top_level.txt
webcrawlerapi_langchain-0.1.1.dist-info/RECORD
