Metadata-Version: 2.4
Name: webcrawlerapi-langchain
Version: 0.1.1
Summary: LangChain integration for WebCrawlerAPI
Home-page: https://github.com/webcrawlerapi/webcrawlerapi-langchain
Author: WebCrawlerAPI
Author-email: support@webcrawlerapi.com
Classifier: Programming Language :: Python :: 3
Classifier: License :: OSI Approved :: MIT License
Classifier: Operating System :: OS Independent
Requires-Python: >=3.8
Requires-Dist: webcrawlerapi>=1.0.8
Requires-Dist: langchain-core>=0.1.0
Dynamic: author
Dynamic: author-email
Dynamic: classifier
Dynamic: description
Dynamic: description-content-type
Dynamic: home-page
Dynamic: requires-dist
Dynamic: requires-python
Dynamic: summary
